{
  "your": {
    "chinese": "你的",
    "pass": false,
    "extraction_count": 3,
    "correct_count": 0,
    "wrong_count": 1,
    "time": "2026-03-13T12:12:18.736Z"
  },
  "like": {
    "chinese": "喜欢,像",
    "pass": false,
    "extraction_count": 3,
    "correct_count": 4,
    "wrong_count": 0,
    "time": "2026-03-13T12:12:18.736Z"
  },
  "make": {
    "chinese": "使,制作",
    "pass": false,
    "extraction_count": 3,
    "correct_count": 0,
    "wrong_count": 0,
    "time": "2026-03-13T12:12:18.736Z"
  },
  "hello": {
    "chinese": "你好",
    "pass": false,
    "extraction_count": 3,
    "correct_count": 1,
    "wrong_count": 0,
    "time": "2026-03-13T12:12:18.736Z"
  },
  "wrong": {
    "chinese": "错误的",
    "pass": false,
    "extraction_count": 3,
    "correct_count": 0,
    "wrong_count": 0,
    "time": "2026-03-13T12:12:18.736Z"
  },
  "can": {
    "chinese": "可以",
    "pass": false,
    "extraction_count": 3,
    "correct_count": 0,
    "wrong_count": 0,
    "time": "2026-03-13T12:12:18.736Z"
  },
  "name": {
    "chinese": "名称",
    "pass": false,
    "extraction_count": 3,
    "correct_count": 1,
    "wrong_count": 0,
    "time": "2026-03-13T12:12:18.736Z"
  },
  "get": {
    "chinese": "得到",
    "pass": false,
    "extraction_count": 3,
    "correct_count": 1,
    "wrong_count": 0,
    "time": "2026-03-13T12:12:18.736Z"
  },
  "really": {
    "chinese": "真正地",
    "pass": false,
    "extraction_count": 3,
    "correct_count": 0,
    "wrong_count": 1,
    "time": "2026-03-13T12:12:18.736Z"
  },
  "first": {
    "chinese": "第一",
    "pass": false,
    "extraction_count": 3,
    "correct_count": 0,
    "wrong_count": 0,
    "time": "2026-03-13T12:12:18.736Z"
  },
  "hear": {
    "chinese": "听到",
    "pass": false,
    "extraction_count": 3,
    "correct_count": 1,
    "wrong_count": 0,
    "time": "2026-03-13T12:12:18.736Z"
  },
  "friends": {
    "chinese": "朋友",
    "pass": false,
    "extraction_count": 3,
    "correct_count": 1,
    "wrong_count": 0,
    "time": "2026-03-13T12:12:18.736Z"
  },
  "advice": {
    "chinese": "建议",
    "pass": false,
    "extraction_count": 3,
    "correct_count": 0,
    "wrong_count": 0,
    "time": "2026-03-13T12:12:18.736Z"
  },
  "best": {
    "chinese": "最好的",
    "pass": false,
    "extraction_count": 3,
    "correct_count": 0,
    "wrong_count": 0,
    "time": "2026-03-13T12:12:18.736Z"
  },
  "school": {
    "chinese": "学校",
    "pass": false,
    "extraction_count": 3,
    "correct_count": 0,
    "wrong_count": 0,
    "time": "2026-03-13T12:12:18.736Z"
  },
  "some": {
    "chinese": "一些",
    "pass": false,
    "extraction_count": 1,
    "correct_count": 0,
    "wrong_count": 0,
    "time": "2026-03-13T12:12:18.736Z"
  },
  "teacher": {
    "chinese": "老师",
    "pass": false,
    "extraction_count": 1,
    "correct_count": 0,
    "wrong_count": 0,
    "time": "2026-03-13T12:12:18.736Z"
  }
}